{
 "actions": [],
 "allow_rename": 1,
 "creation": "2022-09-01 17:32:42.760227",
 "doctype": "DocType",
 "editable_grid": 1,
 "engine": "InnoDB",
 "field_order": [
  "diamond_quality",
  "diamond_grade_1",
  "diamond_grade_2",
  "diamond_grade_3",
  "diamond_grade_4"
 ],
 "fields": [
  {
   "fieldname": "diamond_quality",
   "fieldtype": "Link",
   "in_list_view": 1,
   "in_preview": 1,
   "label": "Diamond Quality",
   "options": "Attribute Value"
  },
  {
   "fieldname": "diamond_grade_1",
   "fieldtype": "Link",
   "label": "Diamond Grade 1",
   "options": "Attribute Value"
  },
  {
   "fieldname": "diamond_grade_2",
   "fieldtype": "Link",
   "label": "Diamond Grade 2",
   "options": "Attribute Value"
  },
  {
   "fieldname": "diamond_grade_3",
   "fieldtype": "Link",
   "label": "Diamond Grade 3",
   "options": "Attribute Value"
  },
  {
   "fieldname": "diamond_grade_4",
   "fieldtype": "Link",
   "label": "Diamond Grade 4",
   "options": "Attribute Value"
  }
 ],
 "index_web_pages_for_search": 1,
 "istable": 1,
 "links": [],
 "modified": "2023-05-11 14:07:00.115125",
 "modified_by": "Administrator",
 "module": "Gurukrupa Exports",
 "name": "Customer Diamond Grade",
 "owner": "Administrator",
 "permissions": [],
 "sort_field": "modified",
 "sort_order": "DESC",
 "states": []
}